Lab5/src/rtl/define.v
/* file: define.v
 Description: This file contains global definitions and parameters for the project.
 Author: Jeremy Cai
 Date: Feb. 9, 2026
 Version: 1.0
 */

//Data width definition
`define DATA_WIDTH 64 //Maximum 64 due to KSA design
`define ALU_OP_WIDTH 4

//ALU operation codes (4 bits)
//Support list: ADD SUB AND OR XNOR CMP LSL LSR SBCMP LSTC RSTC
`define ALU_OP_ADD 4'b0000
`define ALU_OP_SUB 4'b0001
`define ALU_OP_AND 4'b0010
`define ALU_OP_OR  4'b0011
`define ALU_OP_XNOR 4'b0100
`define ALU_OP_CMP 4'b0101
`define ALU_OP_LSL 4'b0110
`define ALU_OP_LSR 4'b0111
// Not standard ALU operation and not used by Arm ISA
`define ALU_OP_SBCMP 4'b1000
`define ALU_OP_LSTC 4'b1001
`define ALU_OP_RSTC 4'b1010

//Register file parameters
`define REG_ADDR_WIDTH 5 //5 bits for 32 registers
`define REG_DATA_WIDTH 64 //64-bit registers

Lab5/src/rtl/component/ppl_reg.v
/* file: ppl_reg.v
 Description: Configurable register moduld for pipeline registers
 Author: Jeremy Cai
 Date: Feb. 8, 2026
 Version: 1.0
 */

`ifndef PPL_REG_V
`define PPL_REG_V

`include "define.v"

module ppl_reg #(parameter NUM_REG = 32)(
    input wire clk, // Clock signal
    input wire rst_n, // Active low reset signal
    input wire en, // Enable signal for updating the register
    input wire [NUM_REG-1:0] D, // Data input
    output reg [NUM_REG-1:0] Q // Data output
);

always @(posedge clk or negedge rst_n) begin
    if (!rst_n) begin
        Q <= 0; // Reset the register output to 0
    end else if (en) begin
        Q <= D; // Update the register output with the input data
    end
end

endmodule

`endif //PPL_REG_V

Lab5/src/rtl/component/regfile.v
/* file: regfile.v
 Description: Register file module for the pipeline CPU design
 Author: Jeremy Cai
 Date: Feb. 9, 2026
 Version: 1.0
 */

`ifndef REGFILE_V
`define REGFILE_V

`include "define.v"

module regfile(
    input clk, // Clock signal. No reset signal needed
    input [`REG_ADDR_WIDTH-1:0] r0addr, // Source register 1 address
    input [`REG_ADDR_WIDTH-1:0] r1addr, // Source register 2 address

    input wena, // Write enable signal
    input [`REG_ADDR_WIDTH-1:0] waddr, // Destination register address
    input [`REG_DATA_WIDTH-1:0] wdata, // Data to write to the register

    output reg [`REG_DATA_WIDTH-1:0] r0data, // Data read from source register 1
    output reg [`REG_DATA_WIDTH-1:0] r1data // Data read from source register 2
);

reg [`REG_DATA_WIDTH-1:0] regfile [0:(1<<`REG_ADDR_WIDTH)-1]; // Register file array

// Register read logic: combinational read
always @(*) begin
    // do not need to qualify with waddr != 0 since Arm doesn't restrict writes to x0
    r0data = regfile[r0addr]; // Register x0 is hardwired to 0
    r1data = regfile[r1addr]; // Register x0 is hardwired to 0
end

// Register write logic: synchronous write on clock edge
always @(posedge clk) begin
    if (wena) begin // do not need to qualify with waddr != 0 since Arm doesn't restrict writes to x0
        regfile[waddr] <= wdata;
    end
end
endmodule

`endif //REGFILE_V

Lab5/src/rtl/component/pc.v
/* file: pc.v
 Description: Program counter module for the pipeline CPU design
 Author: Jeremy Cai
 Date: Feb. 10, 2026
 Version: 1.0
 */

`ifndef PC_V
`define PC_V

`include "define.v"

module pc (
    input wire clk,
    input wire rst_n,
    input wire en, // Enable signal for updating the PC
    
    output reg [`PC_WIDTH-1:0] pc_out // Current value of the program counter
);

// PC update logic: synchronous update on clock edge
always @(posedge clk or negedge rst_n) begin
    if (!rst_n) begin
        pc_out <= 0; // Reset PC to 0 on reset
    end else if (en) begin
        pc_out <= pc_out + 1; // Increment PC by 1 each cycle if enabled
    end
end

endmodule

`endif // PC_V

Lab5/src/rtl/cpu.v
/* file: cpu.v
 Description: CPU module for the pipeline CPU design
 Author: Jeremy Cai
 Date: Feb. 10, 2026
 Version: 1.0 (for Lab 5 only)
 */

`ifndef CPU_V
`define CPU_V

`include "define.v"
`include "pc.v"
`include "ppl_reg.v"
`include "regfile.v"

module cpu (
    input wire clk,
    input wire rst_n,
    // Instruction memory interface
    input wire [`INSTR_WIDTH-1:0] i_mem_data_i, // Instruction memory data input (from i_mem)
    output wire [`INSTR_WIDTH-1:0] i_mem_addr_o, // Instruction memory address output (to i_mem)

    // Data memory interface
    input wire [`DATA_WIDTH-1:0] d_mem_data_i, // Data memory data input (from d_mem)
    output wire [`DATA_WIDTH-1:0] d_mem_addr_o, // Data memory address output (to d_mem)
    output wire [`DATA_WIDTH-1:0] d_mem_data_o, // Data memory data output (to d_mem)
    output wire d_mem_wen_o // Data memory write enable output (to d_mem)
);

// CPU internal signal definitions

//IF stage signals
wire [`PC_WIDTH-1:0] pc_if;
wire pc_en;

assign pc_en = 1'b1; // For now, always enable PC update (no stalls or branches implemented yet)

//Instruction memory interface signals
wire [`INSTR_WIDTH-1:0] instr_if; // Instruction fetched from instruction memory

//ID stage signals
wire [`INSTR_WIDTH-1:0] instr_id; // Instruction in the ID stage (output of IF/ID register)
wire reg_write_id; // Register write enable signal generated in ID stage
wire mem_write_id; // Memory write enable signal generated in ID stage

wire [`REG_ADDR_WIDTH-1:0] rdaddr_id; // Destination register address in ID stage

// Register file interface signals
wire [`REG_ADDR_WIDTH-1:0] r0addr_id; // Source register
wire [`REG_ADDR_WIDTH-1:0] r1addr_id; // Source register
wire [`REG_ADDR_WIDTH-1:0] reg_write_addr; // Destination register
wire [`REG_DATA_WIDTH-1:0] reg_write_data; // Data to write to register
wire reg_write_en; // Register write enable signal for register file generated in ID stage

wire [`REG_DATA_WIDTH-1:0] r0_out_id; // Data read from r0
wire [`REG_DATA_WIDTH-1:0] r1_out_id; // Data read from r1

//No decoding logic or ALU control logic for now.

//EX stage signals
wire reg_write_ex; // Register write enable signal generated in EX stage
wire mem_write_ex; // Memory write enable signal generated in EX stage
wire [`REG_DATA_WIDTH-1:0] r0_out_ex; // Data read from r0 in EX stage
wire [`REG_DATA_WIDTH-1:0] r1_out_ex; // Data read from r1 in EX stage
wire [`REG_ADDR_WIDTH-1:0] rdaddr_ex; // Destination register address in EX stage

//MEM stage signals
wire reg_write_mem; // Register write enable signal generated in MEM stage
wire mem_write_mem; // Memory write enable signal generated in MEM stage
wire [`REG_DATA_WIDTH-1:0] r0_out_mem; // Data read from r0 in MEM stage
wire [`REG_DATA_WIDTH-1:0] r1_out_mem; // ALU result in MEM stage
wire [`REG_ADDR_WIDTH-1:0] rdaddr_mem; // Destination register address in MEM stage

wire [`DATA_WIDTH-1:0] d_mem_data_mem; // Data read from memory in MEM stage

//Data memory interface signals
//Explicitly defined in the interface section for clarity

//WB stage signals
wire reg_write_wb; // Register write enable signal generated in WB stage
wire [`DATA_WIDTH-1:0] d_mem_data_wb; // Data passed from memory in WB stage
wire [`REG_ADDR_WIDTH-1:0] rdaddr_wb; // Destination register address in WB stage


// Start core pipeline logic implementation

/* IF STAGE */
// Instantiate program counter module
pc u_pc (
    .clk(clk),
    .rst_n(rst_n),
    .en(pc_en),
    .pc_out(pc_if)
);

// Connect PC output to instruction memory address output
assign i_mem_addr_o = pc_if;

assign instr_if = i_mem_data_i; // Connect instruction memory data input to IF stage instruction

/* IF/ID pipeline register */
ppl_reg #(.NUM_REG(`INSTR_WIDTH)) if_id_reg (
    .clk(clk),
    .rst_n(rst_n),
    .en(1'b1), // Always enable IF/ID register update for now
    .D(instr_if), // Input is the instruction fetched from instruction memory
    .Q(instr_id) // Output is the instruction for the ID stage
);

/* ID STAGE */
// For now, we will just pass the instruction through the pipeline without decoding or executing it.

//minimal control signal generation logic for memmory pass testing logic to connect instruction to regfile and data memory interfaces
assign mem_write_id = instr_id[31]; // Use the most significant bit of the instruction as a dummy memory write enable signal for testing
assign reg_write_id = instr_id[30]; // Use the second most significant bit of the instruction as a dummy register write enable signal for testing
assign r0addr_id = instr_id[29: 29 - `REG_ADDR_WIDTH + 1]; // Use bits [29:29-`REG_ADDR_WIDTH+1] as the source register address for testing
assign r1addr_id = instr_id[29 - `REG_ADDR_WIDTH: 29 - 2*`REG_ADDR_WIDTH + 1]; // Use bits [29-`REG_ADDR_WIDTH:29-2*`REG_ADDR_WIDTH+1] as the second source register address for testing
assign rdaddr_id = instr_id[29 - 2*`REG_ADDR_WIDTH: 29 - 2*`REG_ADDR_WIDTH - `REG_ADDR_WIDTH + 1]; // Use bits [29-2*`REG_ADDR_WIDTH:29-2*`REG_ADDR_WIDTH-`REG_ADDR_WIDTH+1] as the destination register address for testing

// Register file interface signals
regfile u_regfile (
    .clk(clk),
    .r0addr(r0addr_id),
    .r1addr(r1addr_id),
    .waddr(reg_write_addr),
    .wdata(reg_write_data),
    .wena(reg_write_en),
    .r0data(r0_out_id),
    .r1data(r1_out_id)
);

//ID/EX pipeline register to pass control and data signals from ID stage to EX stage
ppl_reg #(.NUM_REG(1+1+`REG_DATA_WIDTH+`REG_DATA_WIDTH+`REG_ADDR_WIDTH)) id_ex_reg (
    .clk(clk),
    .rst_n(rst_n),
    .en(1'b1), // Always enable ID/EX register update for now
    .D({reg_write_id, mem_write_id, r0_out_id, r1_out_id, rdaddr_id}), // Input is the concatenated control and data signals from ID stage
    .Q({reg_write_ex, mem_write_ex, r0_out_ex, r1_out_ex, rdaddr_ex}) // Output is the separated control and data signals for EX stage
);

/* EX STAGE */
// No ALU or execution logic implemented yet, just passing signals through
ppl_reg #(.NUM_REG(1+1+`REG_DATA_WIDTH+`REG_DATA_WIDTH+`REG_ADDR_WIDTH)) ex_mem_reg (
    .clk(clk),
    .rst_n(rst_n),
    .en(1'b1), // Always enable EX/MEM register update for now
    .D({reg_write_ex, mem_write_ex, r0_out_ex, r1_out_ex, rdaddr_ex}), // Input is the concatenated control and data signals from EX stage
    .Q({reg_write_mem, mem_write_mem, r0_out_mem, r1_out_mem, rdaddr_mem}) // Output is the separated control and data signals for MEM stage
);

/* MEM STAGE */
// Connect data memory interface signals
assign d_mem_addr_o = r0_out_mem; // For now, just use r0_out_mem as the memory address output
assign d_mem_data_o = r1_out_mem; // For now, just use r1_out_mem as the data output to memory
assign d_mem_wen_o = mem_write_mem; // Connect memory write enable signal from MEM stage
assign d_mem_data_mem = d_mem_data_i; // Connect data memory data input to MEM stage data input

ppl_reg #(.NUM_REG(1+`DATA_WIDTH+`REG_ADDR_WIDTH)) mem_wb_reg (
    .clk(clk),
    .rst_n(rst_n),
    .en(1'b1), // Always enable MEM/WB register update for now
    .D({reg_write_mem, d_mem_data_mem, rdaddr_mem}), // Input is the concatenated control and data signals from MEM stage
    .Q({reg_write_wb, d_mem_data_wb, rdaddr_wb}) // Output is the separated control and data signals for WB stage
);

/* WB STAGE */
// Connect register file write interface signals
assign reg_write_data = d_mem_data_wb; // For now, just use the data passed from memory as the data to write to the register file
assign reg_write_addr = rdaddr_wb; // Connect destination register address from WB stage to ID stage
assign reg_write_en = reg_write_wb; // Connect register write enable signal from WB stage to ID stage


endmodule

`endif // CPU_V

Lab5/src/tb/cpu_tb.v
`timescale 1ns/1ps

`include "define.v"
`include "cpu.v"

module cpu_tb;
    reg clk;
    reg rst_n;

    localparam CLK_PERIOD = 10; // Clock period in nanoseconds

    initial clk = 1'b0;
    always #(CLK_PERIOD/2) clk = ~clk; // Generate clock signal

    reg [`INSTR_WIDTH-1:0] i_mem_data_i;
    wire [`INSTR_WIDTH-1:0] i_mem_addr_o;

    reg [`DATA_WIDTH-1:0] d_mem_data_i;
    wire [`DATA_WIDTH-1:0] d_mem_addr_o;
    wire [`DATA_WIDTH-1:0] d_mem_data_o;
    wire d_mem_wen_o;

    cpu u_cpu (
        .clk(clk),
        .rst_n(rst_n),
        .i_mem_data_i(i_mem_data_i),
        .i_mem_addr_o(i_mem_addr_o),
        .d_mem_data_i(d_mem_data_i),
        .d_mem_addr_o(d_mem_addr_o),
        .d_mem_data_o(d_mem_data_o),
        .d_mem_wen_o(d_mem_wen_o)
    );

    // CPU testbench doesn't include actual instruction and data memory models
    localparam I_MEM_DEPTH = 64; // Depth of instruction memory
    reg [`INSTR_WIDTH-1:0] i_mem [0:I_MEM_DEPTH-1];

    always @(*) begin
        i_mem_data_i = i_mem[i_mem_addr_o[5:0]]; // Provide instruction data based on address from CPU
        $display("Instruction memory read: Address = %h, Data = %h", i_mem_addr_o, i_mem_data_i);
    end

    localparam D_MEM_DEPTH = 64; // Depth of data memory
    reg [`DATA_WIDTH-1:0] d_mem [0:D_MEM_DEPTH-1];
    always @(*) begin
        d_mem_data_i = d_mem[d_mem_addr_o[5:0]]; // Provide data based on address from CPU
        $display("Data memory read: Address = %h, Data = %h", d_mem_addr_o, d_mem_data_i);
    end

    always @(posedge clk) begin
        if (d_mem_wen_o) begin
            d_mem[d_mem_addr_o[5:0]] <= d_mem_data_o; // Write data to memory if write enable is asserted
            $display("Data memory write: Address = %h, Data = %h", d_mem_addr_o, d_mem_data_o);
        end
    end

    localparam [`REG_ADDR_WIDTH-1:0] R0 = 0;
    localparam [`REG_ADDR_WIDTH-1:0] R1 = 1;
    localparam [`REG_ADDR_WIDTH-1:0] R2 = 2;
    localparam [`REG_ADDR_WIDTH-1:0] R3 = 3;

    //Instruction builder function for testing
    function [`INSTR_WIDTH-1:0] build_instr;
        input mw;
        input rw;
        input [`REG_ADDR_WIDTH-1:0] rd;
        input [`REG_ADDR_WIDTH-1:0] r0;
        input [`REG_ADDR_WIDTH-1:0] r1;

        begin
            build_instr = {mw, rw, r0, r1, rd, {(`INSTR_WIDTH - 2 - 3 * `REG_ADDR_WIDTH){1'b0}} }; // Simple instruction format for testing
        end
    endfunction

    localparam [`INSTR_WIDTH-1:0] NOP = {`INSTR_WIDTH{1'b0}};

    // Register file initialization — SEPARATE block
    integer k;
    initial begin
        for (k = 0; k < 32; k = k + 1) begin
            u_cpu.u_regfile.regfile[k] = 64'd0;
        end
    end

    integer i;
    integer cycle_cnt;
    integer error_cnt;

    //Start Test
    initial begin
        $display("Initialize testbench...");
        $dumpfile("cpu_tb.vcd");
        $dumpvars(0, cpu_tb);

        rst_n = 0; // Assert reset
        cycle_cnt = 0;
        error_cnt = 0;

        for (i = 0; i < I_MEM_DEPTH; i = i + 1) begin
            i_mem[i] = NOP; // Initialize instruction memory with NOPs
        end
        for (i = 0; i < D_MEM_DEPTH; i = i + 1) begin
            d_mem[i] = {`DATA_WIDTH{1'b0}}; // Initialize data memory with zeros
        end
        
        // Preload some data into memory for testing
        d_mem[0] = 32'd4;
        d_mem[4] = 32'd100;

        //make and load the instruction sequence for testing
        i_mem[0] = build_instr(1'b0, 1'b1, R2, R0, R0);
        i_mem[1] = build_instr(1'b0, 1'b1, R3, R0, R0);
        i_mem[2] = NOP;
        i_mem[3] = NOP;
        i_mem[4] = NOP;
        i_mem[5] = build_instr(1'b1, 1'b0, R0, R2, R3);


        // =============================================
        // Display Test Plan
        // =============================================
        $display("");
        $display("=============================================");
        $display("  CPU Pipeline Testbench");
        $display("=============================================");
        $display("");
        $display("Data Memory (Initial):");
        $display("  Addr | Value");
        $display("  -----|------");
        $display("    0  |   %0d", d_mem[0]);
        $display("    4  | %0d",   d_mem[4]);
        $display("");
        $display("Instruction Memory:");
        $display("  Addr | WME | WRE | REG1 | REG2 | WREG1 | Comments");
        $display("  -----|-----|-----|------|------|-------|---------------------------");
        $display("    0  |  0  |  1  | 000  | XXX  | 002   | Load d_mem[R0] to R2");
        $display("    1  |  0  |  1  | 000  | XXX  | 003   | Load d_mem[R0] to R3");
        $display("    2  |  0  |  0  | XXX  | XXX  | XXX   | Nop");
        $display("    3  |  0  |  0  | XXX  | XXX  | XXX   | Nop - R2=4 by now");
        $display("    4  |  0  |  0  | XXX  | XXX  | XXX   | Nop - R3=4 by now");
        $display("    5  |  1  |  0  | 002  | 003  | XXX   | Store 4 into Mem addr 4");
        $display("");
        $display("Expected: d_mem[4] changes from 100 to 4");
        $display("");

        // =============================================
        // Reset Sequence (hold 3 cycles, release on negedge)
        // =============================================
        repeat (3) @(posedge clk);
        @(negedge clk);
        rst_n = 1'b1;

        $display("[%0t] Reset de-asserted", $time);
        $display("---------------------------------------------");

        // =============================================
        // Run enough cycles for all instructions to retire
        // (6 instructions + 5 pipeline stages + margin)
        // =============================================
        repeat (20) @(posedge clk);

        // =============================================
        // Self-Checking
        // =============================================
        $display("---------------------------------------------");
        $display("");
        $display("Data Memory (Final):");
        $display("  Addr | Value");
        $display("  -----|------");
        $display("    0  |   %0d", d_mem[0]);
        $display("    4  |   %0d", d_mem[4]);
        $display("");

        if (d_mem[4] !== 32'd4) begin
            $display("FAIL: d_mem[4] = %0d, expected 4", d_mem[4]);
            error_cnt = error_cnt + 1;
        end else begin
            $display("PASS: d_mem[4] = 4 (was 100, store succeeded)");
        end

        if (d_mem[0] !== 32'd4) begin
            $display("FAIL: d_mem[0] = %0d, expected 4 (unchanged)", d_mem[0]);
            error_cnt = error_cnt + 1;
        end else begin
            $display("PASS: d_mem[0] = 4 (unchanged as expected)");
        end

        $display("");
        $display("=============================================");
        if (error_cnt == 0)
            $display("  ALL TESTS PASSED");
        else
            $display("  %0d TEST(S) FAILED", error_cnt);
        $display("=============================================");

        $finish;
    end


endmodule

Lab5/src/sim/cpu_tb.vcd
$date
	Wed Feb 11 16:49:18 2026
$end
$version
	Icarus Verilog
$end
$timescale
	1ps
$end
$scope module cpu_tb $end
$var wire 32 ! i_mem_addr_o [31:0] $end
$var wire 1 " d_mem_wen_o $end
$var wire 64 # d_mem_data_o [63:0] $end
$var wire 64 $ d_mem_addr_o [63:0] $end
$var parameter 32 % CLK_PERIOD $end
$var parameter 32 & D_MEM_DEPTH $end
$var parameter 32 ' I_MEM_DEPTH $end
$var parameter 32 ( NOP $end
$var parameter 5 ) R0 $end
$var parameter 5 * R1 $end
$var parameter 5 + R2 $end
$var parameter 5 , R3 $end
$var reg 1 - clk $end
$var reg 64 . d_mem_data_i [63:0] $end
$var reg 32 / i_mem_data_i [31:0] $end
$var reg 1 0 rst_n $end
$var integer 32 1 cycle_cnt [31:0] $end
$var integer 32 2 error_cnt [31:0] $end
$var integer 32 3 i [31:0] $end
$var integer 32 4 k [31:0] $end
$scope function build_instr $end
$var reg 1 5 mw $end
$var reg 5 6 r0 [4:0] $end
$var reg 5 7 r1 [4:0] $end
$var reg 5 8 rd [4:0] $end
$var reg 1 9 rw $end
$upscope $end
$scope module u_cpu $end
$var wire 1 - clk $end
$var wire 64 : d_mem_addr_o [63:0] $end
$var wire 64 ; d_mem_data_i [63:0] $end
$var wire 64 < d_mem_data_mem [63:0] $end
$var wire 64 = d_mem_data_o [63:0] $end
$var wire 1 " d_mem_wen_o $end
$var wire 32 > i_mem_data_i [31:0] $end
$var wire 32 ? instr_if [31:0] $end
$var wire 1 @ pc_en $end
$var wire 5 A reg_write_addr [4:0] $end
$var wire 64 B reg_write_data [63:0] $end
$var wire 1 C reg_write_en $end
$var wire 1 0 rst_n $end
$var wire 1 D reg_write_wb $end
$var wire 1 E reg_write_mem $end
$var wire 1 F reg_write_id $end
$var wire 1 G reg_write_ex $end
$var wire 5 H rdaddr_wb [4:0] $end
$var wire 5 I rdaddr_mem [4:0] $end
$var wire 5 J rdaddr_id [4:0] $end
$var wire 5 K rdaddr_ex [4:0] $end
$var wire 5 L r1addr_id [4:0] $end
$var wire 64 M r1_out_mem [63:0] $end
$var wire 64 N r1_out_id [63:0] $end
$var wire 64 O r1_out_ex [63:0] $end
$var wire 5 P r0addr_id [4:0] $end
$var wire 64 Q r0_out_mem [63:0] $end
$var wire 64 R r0_out_id [63:0] $end
$var wire 64 S r0_out_ex [63:0] $end
$var wire 9 T pc_if [8:0] $end
$var wire 1 U mem_write_mem $end
$var wire 1 V mem_write_id $end
$var wire 1 W mem_write_ex $end
$var wire 32 X instr_id [31:0] $end
$var wire 32 Y i_mem_addr_o [31:0] $end
$var wire 64 Z d_mem_data_wb [63:0] $end
$scope module ex_mem_reg $end
$var wire 135 [ D [134:0] $end
$var wire 1 - clk $end
$var wire 1 \ en $end
$var wire 1 0 rst_n $end
$var parameter 36 ] NUM_REG $end
$var reg 135 ^ Q [134:0] $end
$upscope $end
$scope module id_ex_reg $end
$var wire 135 _ D [134:0] $end
$var wire 1 - clk $end
$var wire 1 ` en $end
$var wire 1 0 rst_n $end
$var parameter 36 a NUM_REG $end
$var reg 135 b Q [134:0] $end
$upscope $end
$scope module if_id_reg $end
$var wire 32 c D [31:0] $end
$var wire 1 - clk $end
$var wire 1 d en $end
$var wire 1 0 rst_n $end
$var parameter 32 e NUM_REG $end
$var reg 32 f Q [31:0] $end
$upscope $end
$scope module mem_wb_reg $end
$var wire 70 g D [69:0] $end
$var wire 1 - clk $end
$var wire 1 h en $end
$var wire 1 0 rst_n $end
$var parameter 34 i NUM_REG $end
$var reg 70 j Q [69:0] $end
$upscope $end
$scope module u_pc $end
$var wire 1 - clk $end
$var wire 1 @ en $end
$var wire 1 0 rst_n $end
$var reg 9 k pc_out [8:0] $end
$upscope $end
$scope module u_regfile $end
$var wire 1 - clk $end
$var wire 5 l r0addr [4:0] $end
$var wire 5 m r1addr [4:0] $end
$var wire 5 n waddr [4:0] $end
$var wire 64 o wdata [63:0] $end
$var wire 1 C wena $end
$var reg 64 p r0data [63:0] $end
$var reg 64 q r1data [63:0] $end
$upscope $end
$upscope $end
$upscope $end
$enddefinitions $end
$comment Show the parameter values. $end
$dumpall
b1000110 i
b100000 e
b10000111 a
b10000111 ]
b11 ,
b10 +
b1 *
b0 )
b0 (
b1000000 '
b1000000 &
b1010 %
$end
#0
$dumpvars
b0 q
b0 p
b0 o
b0 n
b0 m
b0 l
b0 k
b0 j
1h
b10000000 g
b0 f
1d
b1000000000000010000000000000000 c
b0 b
1`
b0 _
b0 ^
1\
b0 [
b0 Z
b0 Y
b0 X
0W
0V
0U
b0 T
b0 S
b0 R
b0 Q
b0 P
b0 O
b0 N
b0 M
b0 L
b0 K
b0 J
b0 I
b0 H
0G
0F
0E
0D
0C
b0 B
b0 A
1@
b1000000000000010000000000000000 ?
b1000000000000010000000000000000 >
b0 =
b100 <
b100 ;
b0 :
09
b0 8
b11 7
b10 6
15
b100000 4
b1000000 3
b0 2
b0 1
00
b1000000000000010000000000000000 /
b100 .
0-
b0 $
b0 #
0"
b0 !
$end
#5000
1-
#10000
0-
#15000
1-
#20000
0-
#25000
1-
#30000
10
0-
#35000
b1000000000000011000000000000000 ?
b1000000000000011000000000000000 c
b1000000000000011000000000000000 /
b1000000000000011000000000000000 >
b10 J
b100000000000000000000000000000000000000000000000000000000000000000000000000000000000000000000000000000000000000000000000000000000000010 _
1F
b100 B
b100 o
b100 Z
b1 !
b1 Y
b1 T
b1 k
b1000000000000010000000000000000 X
b1000000000000010000000000000000 f
b10000000 j
1-
#40000
0-
#45000
b10 K
b100000000000000000000000000000000000000000000000000000000000000000000000000000000000000000000000000000000000000000000000000000000000010 [
1G
b100000000000000000000000000000000000000000000000000000000000000000000000000000000000000000000000000000000000000000000000000000000000011 _
b11 J
b0 ?
b0 c
b0 /
b0 >
b100000000000000000000000000000000000000000000000000000000000000000000000000000000000000000000000000000000000000000000000000000000000010 b
b1000000000000011000000000000000 X
b1000000000000011000000000000000 f
b10 !
b10 Y
b10 T
b10 k
1-
#50000
0-
#55000
b0 J
b0 _
0F
b100000000000000000000000000000000000000000000000000000000000000000000000000000000000000000000000000000000000000000000000000000000000011 [
b11 K
b10 I
b1000000000000000000000000000000000000000000000000000000000000010000010 g
1E
b11 !
b11 Y
b11 T
b11 k
b0 X
b0 f
b100000000000000000000000000000000000000000000000000000000000000000000000000000000000000000000000000000000000000000000000000000000000011 b
b100000000000000000000000000000000000000000000000000000000000000000000000000000000000000000000000000000000000000000000000000000000000010 ^
1-
#60000
0-
#65000
b10 A
b10 n
b10 H
1C
1D
b1000000000000000000000000000000000000000000000000000000000000010000011 g
b11 I
b0 K
b0 [
0G
b1000000000000000000000000000000000000000000000000000000000000010000010 j
b100000000000000000000000000000000000000000000000000000000000000000000000000000000000000000000000000000000000000000000000000000000000011 ^
b0 b
b100 !
b100 Y
b100 T
b100 k
1-
#70000
0-
#75000
b10000100001100000000000000000000 ?
b10000100001100000000000000000000 c
b10000100001100000000000000000000 /
b10000100001100000000000000000000 >
b0 I
b10000000 g
0E
b11 A
b11 n
b11 H
b101 !
b101 Y
b101 T
b101 k
b0 ^
b1000000000000000000000000000000000000000000000000000000000000010000011 j
1-
#80000
0-
#85000
b100 N
b100 q
b100 R
b100 p
b0 A
b0 n
b0 H
0C
0D
b11 L
b11 m
b10 P
b10 l
b10000000000000000000000000000000000000000000000000000000000000100000000000000000000000000000000000000000000000000000000000000010000000 _
1V
b0 ?
b0 c
b0 /
b0 >
b10000000 j
b10000100001100000000000000000000 X
b10000100001100000000000000000000 f
b110 !
b110 Y
b110 T
b110 k
1-
#90000
0-
#95000
b0 N
b0 q
b0 R
b0 p
b0 L
b0 m
b0 P
b0 l
b0 _
0V
b100 O
b100 S
b10000000000000000000000000000000000000000000000000000000000000100000000000000000000000000000000000000000000000000000000000000010000000 [
1W
b111 !
b111 Y
b111 T
b111 k
b0 X
b0 f
b10000000000000000000000000000000000000000000000000000000000000100000000000000000000000000000000000000000000000000000000000000010000000 b
1-
#100000
0-
#105000
b110010000000 g
b1100100 <
b1100100 .
b1100100 ;
b100 #
b100 =
b100 M
b100 $
b100 :
b100 Q
1"
1U
b0 O
b0 S
b0 [
0W
b10000000000000000000000000000000000000000000000000000000000000100000000000000000000000000000000000000000000000000000000000000010000000 ^
b0 b
b1000 !
b1000 Y
b1000 T
b1000 k
1-
#110000
0-
#115000
b0 #
b0 =
b0 M
b0 $
b0 :
b0 Q
0"
0U
b1100100 B
b1100100 o
b1100100 Z
b10000000 g
b100 <
b100 .
b100 ;
b1001 !
b1001 Y
b1001 T
b1001 k
b0 ^
b110010000000 j
1-
#120000
0-
#125000
b100 B
b100 o
b100 Z
b10000000 j
b1010 !
b1010 Y
b1010 T
b1010 k
1-
#130000
0-
#135000
b1011 !
b1011 Y
b1011 T
b1011 k
1-
#140000
0-
#145000
b1100 !
b1100 Y
b1100 T
b1100 k
1-
#150000
0-
#155000
b1101 !
b1101 Y
b1101 T
b1101 k
1-
#160000
0-
#165000
b1110 !
b1110 Y
b1110 T
b1110 k
1-
#170000
0-
#175000
b1111 !
b1111 Y
b1111 T
b1111 k
1-
#180000
0-
#185000
b10000 !
b10000 Y
b10000 T
b10000 k
1-
#190000
0-
#195000
b10001 !
b10001 Y
b10001 T
b10001 k
1-
#200000
0-
#205000
b10010 !
b10010 Y
b10010 T
b10010 k
1-
#210000
0-
#215000
b10011 !
b10011 Y
b10011 T
b10011 k
1-
#220000
0-
#225000
b10100 !
b10100 Y
b10100 T
b10100 k
1-
