Lab5/src/rtl/define.v
/* file: define.v
 Description: This file contains global definitions and parameters for the project.
 Author: Jeremy Cai
 Date: Feb. 9, 2026
 Version: 1.0
 */

//Data width definition
`define DATA_WIDTH 64 //Maximum 64 due to KSA design
`define ALU_OP_WIDTH 4

//ALU operation codes (4 bits)
//Support list: ADD SUB AND OR XNOR CMP LSL LSR SBCMP LSTC RSTC
`define ALU_OP_ADD 4'b0000
`define ALU_OP_SUB 4'b0001
`define ALU_OP_AND 4'b0010
`define ALU_OP_OR  4'b0011
`define ALU_OP_XNOR 4'b0100
`define ALU_OP_CMP 4'b0101
`define ALU_OP_LSL 4'b0110
`define ALU_OP_LSR 4'b0111
// Not standard ALU operation and not used by Arm ISA
`define ALU_OP_SBCMP 4'b1000
`define ALU_OP_LSTC 4'b1001
`define ALU_OP_RSTC 4'b1010

//Register file parameters
`define REG_ADDR_WIDTH 5 //5 bits for 32 registers
`define REG_DATA_WIDTH 64 //64-bit registers

Lab5/src/rtl/component/ppl_reg.v
/* file: ppl_reg.v
 Description: Configurable register moduld for pipeline registers
 Author: Jeremy Cai
 Date: Feb. 8, 2026
 Version: 1.0
 */

`ifndef PPL_REG_V
`define PPL_REG_V

`include "define.v"

module ppl_reg #(parameter NUM_REG = 32)(
    input wire clk, // Clock signal
    input wire rst_n, // Active low reset signal
    input wire en, // Enable signal for updating the register
    input wire [NUM_REG-1:0] D, // Data input
    output reg [NUM_REG-1:0] Q // Data output
);

always @(posedge clk or negedge rst_n) begin
    if (!rst_n) begin
        Q <= 0; // Reset the register output to 0
    end else if (en) begin
        Q <= D; // Update the register output with the input data
    end
end

endmodule

`endif //PPL_REG_V

Lab5/src/rtl/component/regfile.v
/* file: regfile.v
 Description: Register file module for the pipeline CPU design
 Author: Jeremy Cai
 Date: Feb. 9, 2026
 Version: 1.0
 */

`ifndef REGFILE_V
`define REGFILE_V

`include "define.v"

module regfile(
    input clk, // Clock signal. No reset signal needed
    input [`REG_ADDR_WIDTH-1:0] r0addr, // Source register 1 address
    input [`REG_ADDR_WIDTH-1:0] r1addr, // Source register 2 address

    input wena, // Write enable signal
    input [`REG_ADDR_WIDTH-1:0] waddr, // Destination register address
    input [`REG_DATA_WIDTH-1:0] wdata, // Data to write to the register

    output reg [`REG_DATA_WIDTH-1:0] r0data, // Data read from source register 1
    output reg [`REG_DATA_WIDTH-1:0] r1data // Data read from source register 2
);

reg [`REG_DATA_WIDTH-1:0] regfile [0:(1<<`REG_ADDR_WIDTH)-1]; // Register file array

// Register read logic: combinational read
always @(*) begin
    // do not need to qualify with waddr != 0 since Arm doesn't restrict writes to x0
    r0data = regfile[r0addr]; // Register x0 is hardwired to 0
    r1data = regfile[r1addr]; // Register x0 is hardwired to 0
end

// Register write logic: synchronous write on clock edge
always @(posedge clk) begin
    if (wena) begin // do not need to qualify with waddr != 0 since Arm doesn't restrict writes to x0
        regfile[waddr] <= wdata;
    end
end
endmodule

`endif //REGFILE_V

Lab5/src/rtl/component/pc.v
/* file: pc.v
 Description: Program counter module for the pipeline CPU design
 Author: Jeremy Cai
 Date: Feb. 10, 2026
 Version: 1.0
 */

`ifndef PC_V
`define PC_V

`include "define.v"

module pc (
    input wire clk,
    input wire rst_n,
    input wire en, // Enable signal for updating the PC
    
    output reg [`PC_WIDTH-1:0] pc_out // Current value of the program counter
);

// PC update logic: synchronous update on clock edge
always @(posedge clk or negedge rst_n) begin
    if (!rst_n) begin
        pc_out <= 0; // Reset PC to 0 on reset
    end else if (en) begin
        pc_out <= pc_out + 1; // Increment PC by 1 each cycle if enabled
    end
end

endmodule

`endif // PC_V

Lab5/src/rtl/cpu.v
/* file: cpu.v
 Description: CPU module for the pipeline CPU design
 Author: Jeremy Cai
 Date: Feb. 10, 2026
 Version: 1.2
 */

`ifndef CPU_V
`define CPU_V

`include "define.v"
`include "pc.v"
`include "ppl_reg.v"
`include "regfile.v"

module cpu (
    input wire clk,
    input wire rst_n,
    // Instruction memory interface
    input wire [`INSTR_WIDTH-1:0] i_mem_data_i, // Instruction memory data input (from i_mem)
    output wire [`PC_WIDTH-1:0] i_mem_addr_o, // Instruction memory address output (to i_mem)

    // Data memory interface
    input wire [`DATA_WIDTH-1:0] d_mem_data_i, // Data memory data input (from d_mem)
    output wire [`DMEM_ADDR_WIDTH-1:0] d_mem_addr_o, // Data memory address output (to d_mem)
    output wire [`DATA_WIDTH-1:0] d_mem_data_o, // Data memory data output (to d_mem)
    output wire d_mem_wen_o, // Data memory write enable output (to d_mem)
    output wire cpu_done

);

assign cpu_done = (pc_if == {`PC_WIDTH{1'b1}});

// CPU internal signal definitions

//IF stage signals
wire [`PC_WIDTH-1:0] pc_if;
wire pc_en;

assign pc_en = 1'b1;

//Instruction memory interface signals
wire [`INSTR_WIDTH-1:0] instr_if;

//ID stage signals
wire [`INSTR_WIDTH-1:0] instr_id;
wire reg_write_id;
wire mem_write_id;

wire [`REG_ADDR_WIDTH-1:0] rdaddr_id;

// Register file interface signals
wire [`REG_ADDR_WIDTH-1:0] r0addr_id;
wire [`REG_ADDR_WIDTH-1:0] r1addr_id;
wire [`REG_ADDR_WIDTH-1:0] reg_write_addr;
wire [`REG_DATA_WIDTH-1:0] reg_write_data;
wire reg_write_en;

wire [`REG_DATA_WIDTH-1:0] r0_out_id;
wire [`REG_DATA_WIDTH-1:0] r1_out_id;

//EX stage signals
wire reg_write_ex;
wire mem_write_ex;
wire [`REG_DATA_WIDTH-1:0] r0_out_ex;
wire [`REG_DATA_WIDTH-1:0] r1_out_ex;
wire [`REG_ADDR_WIDTH-1:0] rdaddr_ex;

//MEM stage signals
wire reg_write_mem;
wire mem_write_mem;
wire [`REG_DATA_WIDTH-1:0] r0_out_mem;
wire [`REG_DATA_WIDTH-1:0] r1_out_mem;
wire [`REG_ADDR_WIDTH-1:0] rdaddr_mem;

// WB stage signals
wire reg_write_wb;
wire [`REG_ADDR_WIDTH-1:0] rdaddr_wb;


// Start core pipeline logic implementation

/* IF STAGE */
pc u_pc (
    .clk(clk),
    .rst_n(rst_n),
    .en(pc_en),
    .pc_out(pc_if)
);

assign i_mem_addr_o = pc_if;
assign instr_if = i_mem_data_i;

/* IF/ID pipeline register */
ppl_reg #(.NUM_REG(`INSTR_WIDTH)) if_id_reg (
    .clk(clk),
    .rst_n(rst_n),
    .en(1'b1),
    .D(instr_if),
    .Q(instr_id)
);

/* ID STAGE */
// Control Signals
assign mem_write_id = instr_id[31];
assign reg_write_id = instr_id[30];

// Based on soc_tb.v hex codes:
// Load  (40400000): Dest=R2 (Bits 23:21=010), SrcAddr=R0 (Bits 27:24=0000)
// Store (93000000): SrcAddr=R3 (Bits 27:24=0011), SrcData=R2 (Bits 29:27=010)

assign r0addr_id = {1'b0, instr_id[27:24]}; // Address Source (R0 for Load, R3 for Store)
assign r1addr_id = {2'b0, instr_id[29:27]}; // Data Source (R2 for Store)
assign rdaddr_id = {2'b0, instr_id[23:21]}; // Destination (R2/R3 for Load)

regfile u_regfile (
    .clk(clk),
    .r0addr(r0addr_id),
    .r1addr(r1addr_id),
    .waddr(reg_write_addr),
    .wdata(reg_write_data),
    .wena(reg_write_en),
    .r0data(r0_out_id),
    .r1data(r1_out_id)
);

//ID/EX pipeline register
ppl_reg #(.NUM_REG(1+1+`REG_DATA_WIDTH+`REG_DATA_WIDTH+`REG_ADDR_WIDTH)) id_ex_reg (
    .clk(clk),
    .rst_n(rst_n),
    .en(1'b1),
    .D({reg_write_id, mem_write_id, r0_out_id, r1_out_id, rdaddr_id}),
    .Q({reg_write_ex, mem_write_ex, r0_out_ex, r1_out_ex, rdaddr_ex})
);

/* EX STAGE */
ppl_reg #(.NUM_REG(1+1+`REG_DATA_WIDTH+`REG_DATA_WIDTH+`REG_ADDR_WIDTH)) ex_mem_reg (
    .clk(clk),
    .rst_n(rst_n),
    .en(1'b1),
    .D({reg_write_ex, mem_write_ex, r0_out_ex, r1_out_ex, rdaddr_ex}),
    .Q({reg_write_mem, mem_write_mem, r0_out_mem, r1_out_mem, rdaddr_mem})
);

/* MEM STAGE */
// Connect data memory interface signals
assign d_mem_addr_o = r0_out_mem; // Address from R0/R3
assign d_mem_data_o = r1_out_mem; // Data to write from R2
assign d_mem_wen_o = mem_write_mem;

// We do NOT latch d_mem_data_i here. It arrives in the next cycle (WB stage).

// MEM/WB pipeline register
ppl_reg #(.NUM_REG(1+`REG_ADDR_WIDTH)) mem_wb_reg (
    .clk(clk),
    .rst_n(rst_n),
    .en(1'b1),
    .D({reg_write_mem, rdaddr_mem}), // Pass control signals only
    .Q({reg_write_wb, rdaddr_wb})
);

/* WB STAGE */
// SYNC READ FIX:
// Connect d_mem_data_i directly to register write data.
// The data requested in MEM stage is available now.
assign reg_write_data = d_mem_data_i;

assign reg_write_addr = rdaddr_wb;
assign reg_write_en = reg_write_wb;

endmodule

`endif // CPU_V

Lab5/src/tb/cpu_tb.v
/* file: cpu_tb.v
 * Description: CPU Testbench
 *   Verifies the CPU standalone using the same instruction encoding
 *   and logic as the SoC testbench.
 */

`timescale 1ns/1ps

`include "define.v"
`include "cpu.v"

module cpu_tb;
    reg clk;
    reg rst_n;

    localparam CLK_PERIOD = 10; // Clock period in nanoseconds

    initial clk = 1'b0;
    always #(CLK_PERIOD/2) clk = ~clk; // Generate clock signal

    // ========================================================================
    // CPU Interface Signals
    // ========================================================================
    reg  [`INSTR_WIDTH-1:0]     i_mem_data_i;
    wire [`PC_WIDTH-1:0]        i_mem_addr_o;

    reg  [`DATA_WIDTH-1:0]      d_mem_data_i;
    wire [`DMEM_ADDR_WIDTH-1:0] d_mem_addr_o;
    wire [`DATA_WIDTH-1:0]      d_mem_data_o;
    wire                        d_mem_wen_o;
    wire                        cpu_done;

    // ========================================================================
    // DUT Instantiation
    // ========================================================================
    cpu u_cpu (
        .clk          (clk),
        .rst_n        (rst_n),
        .i_mem_data_i (i_mem_data_i),
        .i_mem_addr_o (i_mem_addr_o),
        .d_mem_data_i (d_mem_data_i),
        .d_mem_addr_o (d_mem_addr_o),
        .d_mem_data_o (d_mem_data_o),
        .d_mem_wen_o  (d_mem_wen_o),
        .cpu_done     (cpu_done)
    );

    // ========================================================================
    // Memory Models
    // ========================================================================
    // Note: Using Word Addressing (Index = Address) to match soc_tb.v behavior.
    
    // --- Instruction Memory ---
    localparam I_MEM_DEPTH = 64; 
    reg [`INSTR_WIDTH-1:0] i_mem [0:I_MEM_DEPTH-1];

    always @(*) begin
        // Async read for IMEM
        i_mem_data_i = i_mem[i_mem_addr_o[5:0]]; 
    end

    // --- Data Memory ---
    localparam D_MEM_DEPTH = 64; 
    reg [`DATA_WIDTH-1:0] d_mem [0:D_MEM_DEPTH-1];

    // Async read for DMEM (CPU pipeline registers handle the timing)
    always @(*) begin
        d_mem_data_i = d_mem[d_mem_addr_o[5:0]];
    end

    // Sync write for DMEM
    always @(posedge clk) begin
        if (d_mem_wen_o) begin
            d_mem[d_mem_addr_o[5:0]] <= d_mem_data_o;
            $display("[%0t] Data Memory WRITE: Addr=%0d Data=%0d (0x%h)", 
                     $time, d_mem_addr_o, d_mem_data_o, d_mem_data_o);
        end
    end

    // ========================================================================
    // Instruction Builder (Matches cpu.v decoding logic)
    // ========================================================================
    localparam [`REG_ADDR_WIDTH-1:0] R0 = 0;
    localparam [`REG_ADDR_WIDTH-1:0] R1 = 1;
    localparam [`REG_ADDR_WIDTH-1:0] R2 = 2;
    localparam [`REG_ADDR_WIDTH-1:0] R3 = 3;

    function [`INSTR_WIDTH-1:0] build_instr;
        input mw;                       // Mem Write (Bit 31)
        input rw;                       // Reg Write (Bit 30)
        input [`REG_ADDR_WIDTH-1:0] rd; // Dest      (Bits 23:21)
        input [`REG_ADDR_WIDTH-1:0] r0; // Addr Base (Bits 27:24)
        input [`REG_ADDR_WIDTH-1:0] r1; // Data Src  (Bits 29:27)
        
        reg [31:0] tmp;
        begin
            tmp = 32'b0;
            tmp[31] = mw;
            tmp[30] = rw;
            
            // r1 (Data Source) -> Bits 29:27
            tmp[29:27] = r1[2:0];
            
            // r0 (Addr Source) -> Bits 27:24
            // Note: Bit 27 is shared. We OR them to combine.
            // This logic works for the specific R2/R3 cases in the test.
            tmp[27:24] = tmp[27:24] | r0[3:0];
            
            // rd (Destination) -> Bits 23:21
            tmp[23:21] = rd[2:0];
            
            build_instr = tmp;
        end
    endfunction

    localparam [`INSTR_WIDTH-1:0] NOP = {`INSTR_WIDTH{1'b0}};

    // ========================================================================
    // Main Test Sequence
    // ========================================================================
    integer k, i;
    integer error_cnt;

    // Initialize Register File (Backdoor access to avoid X propagation)
    initial begin
        for (k = 0; k < 32; k = k + 1) begin
            u_cpu.u_regfile.regfile[k] = 64'd0;
        end
    end

    initial begin
        $dumpfile("cpu_tb.vcd");
        $dumpvars(0, cpu_tb);

        // 1. Initialize
        rst_n = 0;
        error_cnt = 0;
        
        for (i = 0; i < I_MEM_DEPTH; i = i + 1) i_mem[i] = NOP;
        for (i = 0; i < D_MEM_DEPTH; i = i + 1) d_mem[i] = 0;

        // 2. Load Data Memory
        // soc_tb.v setup: d_mem[0]=4, d_mem[4]=100
        d_mem[0] = 32'd4;
        d_mem[4] = 32'd100;

        // 3. Load Instruction Memory
        // Op 0: Load R2 from d_mem[R0] (R0=0 -> Addr 0 -> Val 4)
        //       MW=0, RW=1, RD=R2, R0=R0, R1=0
        i_mem[0] = build_instr(1'b0, 1'b1, R2, R0, R0);

        // Op 1: Load R3 from d_mem[R0] (R0=0 -> Addr 0 -> Val 4)
        //       MW=0, RW=1, RD=R3, R0=R0, R1=0
        i_mem[1] = build_instr(1'b0, 1'b1, R3, R0, R0);

        // NOPs for pipeline hazards
        i_mem[2] = NOP;
        i_mem[3] = NOP;
        i_mem[4] = NOP;

        // Op 5: Store R2 to d_mem[R3] (R3=4 -> Addr 4)
        //       MW=1, RW=0, RD=0, R0=R3(Addr), R1=R2(Data)
        //       Writes value 4 (from R2) to Addr 4.
        i_mem[5] = build_instr(1'b1, 1'b0, R0, R3, R2);

        // 4. Display Test Plan
        $display("");
        $display("==================================================");
        $display("  CPU Testbench (Synced with soc_tb.v decoding)");
        $display("==================================================");
        $display("Initial State:");
        $display("  d_mem[0] = %0d (Addr for indirect access)", d_mem[0]);
        $display("  d_mem[4] = %0d (Target to overwrite)", d_mem[4]);
        $display("--------------------------------------------------");
        
        // 5. Run Test
        repeat (3) @(posedge clk);
        rst_n = 1;
        $display("[%0t] Reset Released", $time);

        // Wait for execution (Fetch + Decode + Ex + Mem + WB)
        repeat (20) @(posedge clk);

        // 6. Verify Results
        $display("--------------------------------------------------");
        $display("Final State:");
        $display("  d_mem[0] = %0d (Expected 4)", d_mem[0]);
        $display("  d_mem[4] = %0d (Expected 4)", d_mem[4]);
        $display("");

        // Check Target
        if (d_mem[4] !== 32'd4) begin
            $display("  [FAIL] d_mem[4] = %0d (Expected 4)", d_mem[4]);
            error_cnt = error_cnt + 1;
        end else begin
            $display("  [PASS] Store successful (100 -> 4).");
        end

        // Check Source Integrity
        if (d_mem[0] !== 32'd4) begin
            $display("  [FAIL] d_mem[0] corrupted! val=%0d", d_mem[0]);
            error_cnt = error_cnt + 1;
        end else begin
            $display("  [PASS] Source memory unchanged.");
        end

        $display("==================================================");
        if (error_cnt == 0) $display("  >>> ALL TESTS PASSED <<<");
        else                $display("  >>> %0d FAILURES <<<", error_cnt);
        $display("==================================================");
        
        $finish;
    end

endmodule

Lab5/src/sim/cpu_tb.vcd
$date
	Fri Feb 13 15:51:10 2026
$end
$version
	Icarus Verilog
$end
$timescale
	1ps
$end
$scope module cpu_tb $end
$var wire 9 ! i_mem_addr_o [8:0] $end
$var wire 1 " d_mem_wen_o $end
$var wire 64 # d_mem_data_o [63:0] $end
$var wire 8 $ d_mem_addr_o [7:0] $end
$var wire 1 % cpu_done $end
$var parameter 32 & CLK_PERIOD $end
$var parameter 32 ' D_MEM_DEPTH $end
$var parameter 32 ( I_MEM_DEPTH $end
$var parameter 32 ) NOP $end
$var parameter 5 * R0 $end
$var parameter 5 + R1 $end
$var parameter 5 , R2 $end
$var parameter 5 - R3 $end
$var reg 1 . clk $end
$var reg 64 / d_mem_data_i [63:0] $end
$var reg 32 0 i_mem_data_i [31:0] $end
$var reg 1 1 rst_n $end
$var integer 32 2 error_cnt [31:0] $end
$var integer 32 3 i [31:0] $end
$var integer 32 4 k [31:0] $end
$scope function build_instr $end
$var reg 1 5 mw $end
$var reg 5 6 r0 [4:0] $end
$var reg 5 7 r1 [4:0] $end
$var reg 5 8 rd [4:0] $end
$var reg 1 9 rw $end
$var reg 32 : tmp [31:0] $end
$upscope $end
$scope module u_cpu $end
$var wire 1 . clk $end
$var wire 64 ; d_mem_data_i [63:0] $end
$var wire 64 < d_mem_data_o [63:0] $end
$var wire 1 " d_mem_wen_o $end
$var wire 9 = i_mem_addr_o [8:0] $end
$var wire 32 > i_mem_data_i [31:0] $end
$var wire 32 ? instr_if [31:0] $end
$var wire 1 @ pc_en $end
$var wire 5 A reg_write_addr [4:0] $end
$var wire 64 B reg_write_data [63:0] $end
$var wire 1 C reg_write_en $end
$var wire 1 1 rst_n $end
$var wire 1 D reg_write_wb $end
$var wire 1 E reg_write_mem $end
$var wire 1 F reg_write_id $end
$var wire 1 G reg_write_ex $end
$var wire 5 H rdaddr_wb [4:0] $end
$var wire 5 I rdaddr_mem [4:0] $end
$var wire 5 J rdaddr_id [4:0] $end
$var wire 5 K rdaddr_ex [4:0] $end
$var wire 5 L r1addr_id [4:0] $end
$var wire 64 M r1_out_mem [63:0] $end
$var wire 64 N r1_out_id [63:0] $end
$var wire 64 O r1_out_ex [63:0] $end
$var wire 5 P r0addr_id [4:0] $end
$var wire 64 Q r0_out_mem [63:0] $end
$var wire 64 R r0_out_id [63:0] $end
$var wire 64 S r0_out_ex [63:0] $end
$var wire 9 T pc_if [8:0] $end
$var wire 1 U mem_write_mem $end
$var wire 1 V mem_write_id $end
$var wire 1 W mem_write_ex $end
$var wire 32 X instr_id [31:0] $end
$var wire 8 Y d_mem_addr_o [7:0] $end
$var wire 1 % cpu_done $end
$scope module ex_mem_reg $end
$var wire 135 Z D [134:0] $end
$var wire 1 . clk $end
$var wire 1 [ en $end
$var wire 1 1 rst_n $end
$var parameter 36 \ NUM_REG $end
$var reg 135 ] Q [134:0] $end
$upscope $end
$scope module id_ex_reg $end
$var wire 135 ^ D [134:0] $end
$var wire 1 . clk $end
$var wire 1 _ en $end
$var wire 1 1 rst_n $end
$var parameter 36 ` NUM_REG $end
$var reg 135 a Q [134:0] $end
$upscope $end
$scope module if_id_reg $end
$var wire 32 b D [31:0] $end
$var wire 1 . clk $end
$var wire 1 c en $end
$var wire 1 1 rst_n $end
$var parameter 32 d NUM_REG $end
$var reg 32 e Q [31:0] $end
$upscope $end
$scope module mem_wb_reg $end
$var wire 6 f D [5:0] $end
$var wire 1 . clk $end
$var wire 1 g en $end
$var wire 1 1 rst_n $end
$var parameter 33 h NUM_REG $end
$var reg 6 i Q [5:0] $end
$upscope $end
$scope module u_pc $end
$var wire 1 . clk $end
$var wire 1 @ en $end
$var wire 1 1 rst_n $end
$var reg 9 j pc_out [8:0] $end
$upscope $end
$scope module u_regfile $end
$var wire 1 . clk $end
$var wire 5 k r0addr [4:0] $end
$var wire 5 l r1addr [4:0] $end
$var wire 5 m waddr [4:0] $end
$var wire 64 n wdata [63:0] $end
$var wire 1 C wena $end
$var reg 64 o r0data [63:0] $end
$var reg 64 p r1data [63:0] $end
$upscope $end
$upscope $end
$upscope $end
$enddefinitions $end
$comment Show the parameter values. $end
$dumpall
b110 h
b100000 d
b10000111 `
b10000111 \
b11 -
b10 ,
b1 +
b0 *
b0 )
b1000000 (
b1000000 '
b1010 &
$end
#0
$dumpvars
b0 p
b0 o
b100 n
b0 m
b0 l
b0 k
b0 j
b0 i
1g
b0 f
b0 e
1c
b1000000010000000000000000000000 b
b0 a
1_
b0 ^
b0 ]
1[
b0 Z
b0 Y
b0 X
0W
0V
0U
b0 T
b0 S
b0 R
b0 Q
b0 P
b0 O
b0 N
b0 M
b0 L
b0 K
b0 J
b0 I
b0 H
0G
0F
0E
0D
0C
b100 B
b0 A
1@
b1000000010000000000000000000000 ?
b1000000010000000000000000000000 >
b0 =
b0 <
b100 ;
b10010011000000000000000000000000 :
09
b0 8
b10 7
b11 6
15
b100000 4
b1000000 3
b0 2
01
b1000000010000000000000000000000 0
b100 /
0.
0%
b0 $
b0 #
0"
b0 !
$end
#5000
1.
#10000
0.
#15000
1.
#20000
0.
#25000
b10 J
b100000000000000000000000000000000000000000000000000000000000000000000000000000000000000000000000000000000000000000000000000000000000010 ^
1F
b1000000011000000000000000000000 ?
b1000000011000000000000000000000 b
b1000000011000000000000000000000 0
b1000000011000000000000000000000 >
b1000000010000000000000000000000 X
b1000000010000000000000000000000 e
b1 !
b1 =
b1 T
b1 j
11
1.
#30000
0.
#35000
b0 ?
b0 b
b0 0
b0 >
b100000000000000000000000000000000000000000000000000000000000000000000000000000000000000000000000000000000000000000000000000000000000011 ^
b11 J
b10 K
b100000000000000000000000000000000000000000000000000000000000000000000000000000000000000000000000000000000000000000000000000000000000010 Z
1G
b10 !
b10 =
b10 T
b10 j
b1000000011000000000000000000000 X
b1000000011000000000000000000000 e
b100000000000000000000000000000000000000000000000000000000000000000000000000000000000000000000000000000000000000000000000000000000000010 a
1.
#40000
0.
#45000
b10 I
b100010 f
1E
b100000000000000000000000000000000000000000000000000000000000000000000000000000000000000000000000000000000000000000000000000000000000011 Z
b11 K
b0 J
b0 ^
0F
b100000000000000000000000000000000000000000000000000000000000000000000000000000000000000000000000000000000000000000000000000000000000010 ]
b100000000000000000000000000000000000000000000000000000000000000000000000000000000000000000000000000000000000000000000000000000000000011 a
b0 X
b0 e
b11 !
b11 =
b11 T
b11 j
1.
#50000
0.
#55000
b0 K
b0 Z
0G
b100011 f
b11 I
b10 A
b10 m
b10 H
1C
1D
b100 !
b100 =
b100 T
b100 j
b0 a
b100000000000000000000000000000000000000000000000000000000000000000000000000000000000000000000000000000000000000000000000000000000000011 ]
b100010 i
1.
#60000
0.
#65000
b11 A
b11 m
b11 H
b0 I
b0 f
0E
b10010011000000000000000000000000 ?
b10010011000000000000000000000000 b
b10010011000000000000000000000000 0
b10010011000000000000000000000000 >
b100011 i
b0 ]
b101 !
b101 =
b101 T
b101 j
1.
#70000
0.
#75000
b100 N
b100 p
b100 R
b100 o
b0 ?
b0 b
b0 0
b0 >
b10 L
b10 l
b11 P
b11 k
b10000000000000000000000000000000000000000000000000000000000000100000000000000000000000000000000000000000000000000000000000000010000000 ^
1V
b0 A
b0 m
b0 H
0C
0D
b110 !
b110 =
b110 T
b110 j
b10010011000000000000000000000000 X
b10010011000000000000000000000000 e
b0 i
1.
#80000
0.
#85000
b0 N
b0 p
b0 R
b0 o
b100 O
b100 S
b10000000000000000000000000000000000000000000000000000000000000100000000000000000000000000000000000000000000000000000000000000010000000 Z
1W
b0 L
b0 l
b0 P
b0 k
b0 ^
0V
b10000000000000000000000000000000000000000000000000000000000000100000000000000000000000000000000000000000000000000000000000000010000000 a
b0 X
b0 e
b111 !
b111 =
b111 T
b111 j
1.
#90000
0.
#95000
b1100100 B
b1100100 n
b1100100 /
b1100100 ;
b100 $
b100 Y
b0 O
b0 S
b0 Z
0W
b100 #
b100 <
b100 M
b100 Q
1"
1U
b1000 !
b1000 =
b1000 T
b1000 j
b0 a
b10000000000000000000000000000000000000000000000000000000000000100000000000000000000000000000000000000000000000000000000000000010000000 ]
1.
#100000
0.
#105000
b0 $
b0 Y
b0 #
b0 <
b0 M
b0 Q
0"
0U
b100 B
b100 n
b100 /
b100 ;
b0 ]
b1001 !
b1001 =
b1001 T
b1001 j
1.
#110000
0.
#115000
b1010 !
b1010 =
b1010 T
b1010 j
1.
#120000
0.
#125000
b1011 !
b1011 =
b1011 T
b1011 j
1.
#130000
0.
#135000
b1100 !
b1100 =
b1100 T
b1100 j
1.
#140000
0.
#145000
b1101 !
b1101 =
b1101 T
b1101 j
1.
#150000
0.
#155000
b1110 !
b1110 =
b1110 T
b1110 j
1.
#160000
0.
#165000
b1111 !
b1111 =
b1111 T
b1111 j
1.
#170000
0.
#175000
b10000 !
b10000 =
b10000 T
b10000 j
1.
#180000
0.
#185000
b10001 !
b10001 =
b10001 T
b10001 j
1.
#190000
0.
#195000
b10010 !
b10010 =
b10010 T
b10010 j
1.
#200000
0.
#205000
b10011 !
b10011 =
b10011 T
b10011 j
1.
#210000
0.
#215000
b10100 !
b10100 =
b10100 T
b10100 j
1.
#220000
0.
#225000
b10101 !
b10101 =
b10101 T
b10101 j
1.
