Lab5/src/rtl/define.v
/* file: define.v
 Description: This file contains global definitions and parameters for the project.
 Author: Jeremy Cai
 Date: Feb. 9, 2026
 Version: 1.0
 */

//Data width definition
`define DATA_WIDTH 64 //Maximum 64 due to KSA design
`define ALU_OP_WIDTH 4

//ALU operation codes (4 bits)
//Support list: ADD SUB AND OR XNOR CMP LSL LSR SBCMP LSTC RSTC
`define ALU_OP_ADD 4'b0000
`define ALU_OP_SUB 4'b0001
`define ALU_OP_AND 4'b0010
`define ALU_OP_OR  4'b0011
`define ALU_OP_XNOR 4'b0100
`define ALU_OP_CMP 4'b0101
`define ALU_OP_LSL 4'b0110
`define ALU_OP_LSR 4'b0111
// Not standard ALU operation and not used by Arm ISA
`define ALU_OP_SBCMP 4'b1000
`define ALU_OP_LSTC 4'b1001
`define ALU_OP_RSTC 4'b1010

//Register file parameters
`define REG_ADDR_WIDTH 5 //5 bits for 32 registers
`define REG_DATA_WIDTH 64 //64-bit registers

Lab5/src/rtl/component/regfile.v
/* file: regfile.v
 Description: Register file module for the pipeline CPU design
 Author: Jeremy Cai
 Date: Feb. 9, 2026
 Version: 1.0
 */

`ifndef REGFILE_V
`define REGFILE_V

`include "define.v"

module regfile(
    input clk, // Clock signal. No reset signal needed
    input [`REG_ADDR_WIDTH-1:0] r0addr, // Source register 1 address
    input [`REG_ADDR_WIDTH-1:0] r1addr, // Source register 2 address

    input wena, // Write enable signal
    input [`REG_ADDR_WIDTH-1:0] waddr, // Destination register address
    input [`REG_DATA_WIDTH-1:0] wdata, // Data to write to the register

    output wire [`REG_DATA_WIDTH-1:0] r0data, // Data read from source register 1
    output wire [`REG_DATA_WIDTH-1:0] r1data, // Data read from source register 2
    
    // ILA probe signals for debugging
    input [`REG_ADDR_WIDTH-1:0] ila_cpu_reg_addr, // ILA probe address input
    output wire [`REG_DATA_WIDTH-1:0] ila_cpu_reg_data // ILA probe data output
);

reg [`REG_DATA_WIDTH-1:0] regs [0:(1<<`REG_ADDR_WIDTH)-1]; // Register file array

// Register read logic: combinational read
    // do not need to qualify with waddr != 0 since Arm doesn't restrict writes to x0
assign r0data = regs[r0addr]; // Register x0 is hardwired to 0
assign r1data = regs[r1addr]; // Register x0 is hardwired to 0
assign ila_cpu_reg_data = regs[ila_cpu_reg_addr]; // ILA probe data output

// Register write logic: synchronous write on clock edge
always @(posedge clk) begin
    if (wena) begin // do not need to qualify with waddr != 0 since Arm doesn't restrict writes to x0
        regs[waddr] <= wdata;
    end
end
endmodule

`endif //REGFILE_V

Lab5/src/tb/regfile_tb.v
/* file: regfile_tb.v
   Description: Testbench for the Register File
*/

`timescale 1ns / 1ps

`include "define.v"
`include "regfile.v"

module regfile_tb;

    // Inputs
    reg clk;
    reg [`REG_ADDR_WIDTH-1:0] r0addr;
    reg [`REG_ADDR_WIDTH-1:0] r1addr;
    reg wena;
    reg [`REG_ADDR_WIDTH-1:0] waddr;
    reg [`REG_DATA_WIDTH-1:0] wdata;
    reg [`REG_ADDR_WIDTH-1:0] ila_cpu_reg_addr;

    // Outputs
    wire [`REG_DATA_WIDTH-1:0] r0data;
    wire [`REG_DATA_WIDTH-1:0] r1data;
    wire [`REG_DATA_WIDTH-1:0] ila_cpu_reg_data;

    // Instantiate the Unit Under Test (UUT)
    regfile uut (
        .clk(clk), 
        .r0addr(r0addr), 
        .r1addr(r1addr), 
        .wena(wena), 
        .waddr(waddr), 
        .wdata(wdata), 
        .r0data(r0data), 
        .r1data(r1data), 
        .ila_cpu_reg_addr(ila_cpu_reg_addr), 
        .ila_cpu_reg_data(ila_cpu_reg_data)
    );

    // Clock generation (10ns period)
    always #5 clk = ~clk;

    initial begin

        // Initialize Inputs
        clk = 0;
        r0addr = 0;
        r1addr = 0;
        wena = 0;
        waddr = 0;
        wdata = 0;
        ila_cpu_reg_addr = 0;

        // Setup VCD dump for waveform viewing
        $dumpfile("regfile_tb.vcd");
        $dumpvars(0, regfile_tb);

        $display("Starting Regfile Testbench...");

        // ------------------------------------------------------------
        // Test 1: Write to Register 1 and Read back
        // ------------------------------------------------------------
        #10;
        waddr = 5'd1;
        wdata = 32'hDEADBEEF;
        wena = 1;
        #10; // Wait for clock edge
        wena = 0; // Disable write
        
        // Read back on Port 0
        r0addr = 5'd1;
        #1; // Wait for combinational read
        if (r0data === 32'hDEADBEEF) 
            $display("[PASS] Test 1: Write/Read Reg 1. Got: %h", r0data);
        else 
            $display("[FAIL] Test 1: Write/Read Reg 1. Exp: DEADBEEF, Got: %h", r0data);

        // ------------------------------------------------------------
        // Test 2: Write to Register 2 and Dual Read (Port 0 & 1)
        // ------------------------------------------------------------
        #10;
        waddr = 5'd2;
        wdata = 32'hCAFEBABE;
        wena = 1;
        #10;
        wena = 0;

        // Read Reg 1 on Port 0, Reg 2 on Port 1
        r0addr = 5'd1;
        r1addr = 5'd2;
        #1;
        if (r0data === 32'hDEADBEEF && r1data === 32'hCAFEBABE)
            $display("[PASS] Test 2: Dual Port Read. R1: %h, R2: %h", r0data, r1data);
        else
            $display("[FAIL] Test 2: Dual Port Read. R1: %h, R2: %h", r0data, r1data);

        // ------------------------------------------------------------
        // Test 3: Write Enable (wena) Logic
        // ------------------------------------------------------------
        #10;
        waddr = 5'd1;       // Target Register 1 again
        wdata = 32'h00000000; // Try to clear it
        wena = 0;           // But wena is LOW
        #10;
        
        r0addr = 5'd1;
        #1;
        if (r0data === 32'hDEADBEEF)
            $display("[PASS] Test 3: Write Enable Low (Data preserved).");
        else
            $display("[FAIL] Test 3: Write Enable Low. Data changed to: %h", r0data);

        // ------------------------------------------------------------
        // Test 4: ILA Debug Port
        // ------------------------------------------------------------
        #10;
        ila_cpu_reg_addr = 5'd2; // Look at Register 2
        #1;
        if (ila_cpu_reg_data === 32'hCAFEBABE)
            $display("[PASS] Test 4: ILA Port Read. Got: %h", ila_cpu_reg_data);
        else
            $display("[FAIL] Test 4: ILA Port Read. Exp: CAFEBABE, Got: %h", ila_cpu_reg_data);

        // ------------------------------------------------------------
        // Test 5: Register 0 Behavior
        // Note: Based on your code, R0 is NOT hardwired to 0.
        // It acts like a normal register.
        // ------------------------------------------------------------
        #10;
        waddr = 5'd0;
        wdata = 32'h12345678;
        wena = 1;
        #10;
        wena = 0;
        
        r0addr = 5'd0;
        #1;
        if (r0data === 32'h12345678)
            $display("[PASS] Test 5: Reg 0 Write/Read (Normal RAM behavior confirmed).");
        else
            $display("[FAIL] Test 5: Reg 0 Write/Read. Got: %h", r0data);

        $display("Testbench Complete.");
        $finish;
    end

endmodule

Lab5/src/sim/regfile_tb.vcd
$date
	Sat Feb 14 21:08:10 2026
$end
$version
	Icarus Verilog
$end
$timescale
	1ps
$end
$scope module regfile_tb $end
$var wire 64 ! r1data [63:0] $end
$var wire 64 " r0data [63:0] $end
$var wire 64 # ila_cpu_reg_data [63:0] $end
$var reg 1 $ clk $end
$var reg 3 % ila_cpu_reg_addr [2:0] $end
$var reg 3 & r0addr [2:0] $end
$var reg 3 ' r1addr [2:0] $end
$var reg 3 ( waddr [2:0] $end
$var reg 64 ) wdata [63:0] $end
$var reg 1 * wena $end
$scope module uut $end
$var wire 1 $ clk $end
$var wire 3 + ila_cpu_reg_addr [2:0] $end
$var wire 64 , ila_cpu_reg_data [63:0] $end
$var wire 3 - r0addr [2:0] $end
$var wire 64 . r0data [63:0] $end
$var wire 3 / r1addr [2:0] $end
$var wire 64 0 r1data [63:0] $end
$var wire 3 1 waddr [2:0] $end
$var wire 64 2 wdata [63:0] $end
$var wire 1 * wena $end
$upscope $end
$upscope $end
$enddefinitions $end
$comment Show the parameter values. $end
$dumpall
$end
#0
$dumpvars
b0 2
b0 1
bx 0
b0 /
bx .
b0 -
bx ,
b0 +
0*
b0 )
b0 (
b0 '
b0 &
b0 %
0$
bx #
bx "
bx !
$end
#5000
1$
#10000
0$
1*
b11011110101011011011111011101111 )
b11011110101011011011111011101111 2
b1 (
b1 1
#15000
1$
#20000
0$
b11011110101011011011111011101111 "
b11011110101011011011111011101111 .
b1 &
b1 -
0*
#25000
1$
#30000
0$
#31000
1*
b11001010111111101011101010111110 )
b11001010111111101011101010111110 2
b10 (
b10 1
#35000
1$
#40000
0$
#41000
b11001010111111101011101010111110 !
b11001010111111101011101010111110 0
b10 '
b10 /
0*
#45000
1$
#50000
0$
#52000
b0 )
b0 2
b1 (
b1 1
#55000
1$
#60000
0$
#65000
1$
#70000
0$
#73000
b11001010111111101011101010111110 #
b11001010111111101011101010111110 ,
b10 %
b10 +
#75000
1$
#80000
0$
#84000
1*
b10010001101000101011001111000 )
b10010001101000101011001111000 2
b0 (
b0 1
#85000
1$
#90000
0$
#94000
b10010001101000101011001111000 "
b10010001101000101011001111000 .
b0 &
b0 -
0*
